souper-1.1.2-nspkg.pth
souper/interfaces.py
souper/soup.py
souper/soup.rst
souper/tests.py
souper-1.1.2.dist-info/LICENSE.rst
souper-1.1.2.dist-info/METADATA
souper-1.1.2.dist-info/WHEEL
souper-1.1.2.dist-info/namespace_packages.txt
souper-1.1.2.dist-info/top_level.txt
souper-1.1.2.dist-info/RECORD
