Metadata-Version: 2.1
Name: souper
Version: 1.1.2
Summary: Souper - Generic Indexed Storage based on ZODB
Home-page: https://pypi.org/project/souper
Author: BlueDynamics Alliance
Author-email: dev@bluedynamics.com
License: BSD
Keywords: zodb zope pyramid node plone
Platform: UNKNOWN
Classifier: Framework :: ZODB
Classifier: Intended Audience :: Developers
Classifier: License :: OSI Approved :: BSD License
Classifier: Operating System :: OS Independent
Classifier: Programming Language :: Python
Classifier: Programming Language :: Python :: 2.7
Classifier: Programming Language :: Python :: 3.6
Classifier: Programming Language :: Python :: 3.7
Classifier: Topic :: Internet :: WWW/HTTP :: Dynamic Content
Classifier: Development Status :: 5 - Production/Stable
Requires-Dist: node.ext.zodb
Requires-Dist: repoze.catalog (>=0.9.0)
Requires-Dist: setuptools
Requires-Dist: six
